README.md
setup.py
mospipe/extract.py
mospipe/pipeline.py
mospipe/reduce.py
mospipe/version.py
mospipe.egg-info/PKG-INFO
mospipe.egg-info/SOURCES.txt
mospipe.egg-info/dependency_links.txt
mospipe.egg-info/top_level.txt
mospipe/data/MOSFIRE_telluric_correction_long2pos_20170509_H_HIP105437.fits
mospipe/data/MOSFIRE_telluric_correction_long2pos_20170509_J_HIP105437.fits
mospipe/data/MOSFIRE_telluric_correction_long2pos_20170509_K_HIP105437.fits
mospipe/data/MOSFIRE_telluric_correction_long2pos_20170509_Y_HIP105437.fits
mospipe/data/oliva_oh_lines.vot