Metadata-Version: 1.1
Name: mospipe
Version: 1.0
Summary: MOSFIRE pipeline
Home-page: https://github.com/gbrammer/mospipe
Author: Gabriel Brammer
Author-email: gbrammer@gmail.com
License: MIT
Download-URL: https://github.com/gbrammer/mospipe/tarball/1.0
Platform: UNKNOWN
Classifier: Development Status :: 1 - Planning
Classifier: Intended Audience :: Science/Research
Classifier: Topic :: Scientific/Engineering :: Astronomy
